Hardiksonware/__init__.py
Hardiksonware/decrypt.py
Hardiksonware/encrypt.py
Hardiksonware-0.0.6.dist-info/METADATA
Hardiksonware-0.0.6.dist-info/WHEEL
Hardiksonware-0.0.6.dist-info/top_level.txt
Hardiksonware-0.0.6.dist-info/RECORD
